openant/__init__.py
openant/__main__.py
openant/udev_rules.py
openant/base/__init__.py
openant/base/ant.py
openant/base/commons.py
openant/base/datatarget.py
openant/base/driver.py
openant/base/message.py
openant/devices/__init__.py
openant/devices/bike_speed_cadence.py
openant/devices/common.py
openant/devices/controls_device.py
openant/devices/core_temp.py
openant/devices/dropper_seatpost.py
openant/devices/environment.py
openant/devices/fitness_equipment.py
openant/devices/heart_rate.py
openant/devices/lev.py
openant/devices/power_meter.py
openant/devices/scanner.py
openant/devices/shift.py
openant/devices/tire_pressure_monitor.py
openant/devices/utilities.py
openant/easy/__init__.py
openant/easy/channel.py
openant/easy/exception.py
openant/easy/filter.py
openant/easy/node.py
openant/fs/__init__.py
openant/fs/beacon.py
openant/fs/command.py
openant/fs/commandpipe.py
openant/fs/commons.py
openant/fs/file.py
openant/fs/manager.py
openant/subparsers/__init__.py
openant/subparsers/influx.py
openant/subparsers/mqtt.py
openant/subparsers/scan.py
openant/tests/__init__.py
openant/tests/base/__init__.py
openant/tests/base/test_message.py
openant/tests/easy/__init__.py
openant/tests/easy/test.py
openant/tests/fs/__init__.py
openant/tests/fs/test.py
openant/tests/fs/test_beacon.py
openant/tests/fs/test_command.py
openant/tests/fs/test_commandpipe.py
openant/tests/fs/test_file.py
openant-1.3.4.dist-info/licenses/LICENSE
openant-1.3.4.dist-info/METADATA
openant-1.3.4.dist-info/WHEEL
openant-1.3.4.dist-info/entry_points.txt
openant-1.3.4.dist-info/top_level.txt
openant-1.3.4.dist-info/RECORD
