Metadata-Version: 2.4
Name: openant
Version: 1.3.4
Summary: ANT, ANT-FS and ANT+ Python Library
Author: John Whittington
Author-email: Gustav Tiger <gustav@tiger.name>
License: Copyright (c) 2012, Gustav Tiger <gustav@tiger.name>
Classifier: Intended Audience :: Developers
Classifier: Intended Audience :: Healthcare Industry
Classifier: Programming Language :: Python :: 3.8
Classifier: Programming Language :: Python :: 3.9
Classifier: Programming Language :: Python :: 3.10
Classifier: Programming Language :: Python :: 3.11
Classifier: Programming Language :: Python :: 3.12
Classifier: Topic :: Software Development :: Libraries :: Python Modules
Classifier: Topic :: Software Development :: Embedded Systems
Classifier: Environment :: Console
Requires-Python: >=3.8
License-File: LICENSE
Requires-Dist: pyusb>=1.1.1
Provides-Extra: serial
Requires-Dist: pyserial; extra == "serial"
Provides-Extra: influx
Requires-Dist: influxdb-client; extra == "influx"
Provides-Extra: mqtt
Requires-Dist: paho-mqtt; extra == "mqtt"
Provides-Extra: test
Requires-Dist: pytest; extra == "test"
Requires-Dist: black; extra == "test"
Requires-Dist: pylint; extra == "test"
Provides-Extra: docs
Requires-Dist: sphinx>=5.2.3; extra == "docs"
Requires-Dist: furo>=2021.3.20b30; extra == "docs"
Requires-Dist: sphinx_mdinclude; extra == "docs"
Dynamic: license-file
